ab_test/fixtures/__init__.py
ab_test/fixtures/cache/__init__.py
ab_test/fixtures/cache/conftest.py
ab_test/fixtures/database/__init__.py
ab_test/fixtures/database/conftest.py
ab_test_fixtures-0.1.7.dist-info/METADATA
ab_test_fixtures-0.1.7.dist-info/WHEEL
ab_test_fixtures-0.1.7.dist-info/licenses/LICENSE
ab_test_fixtures-0.1.7.dist-info/RECORD
