Metadata-Version: 2.4
Name: ab-test-fixtures
Version: 0.1.7
Author-email: Matthew Coulter <53892067+mattcoulter7@users.noreply.github.com>
License-File: LICENSE
Requires-Python: <4,>=3.12
Requires-Dist: ab-cache<0.2.0,>=0.1.3
Requires-Dist: ab-database[sqlite-async]<0.3.0,>=0.2.1
Requires-Dist: pytest-asyncio<2,>=1.0.0
Requires-Dist: pytest<9,>=8.4.0
